PyVimeo-0.2.1.dist-info/DESCRIPTION.rst
PyVimeo-0.2.1.dist-info/METADATA
PyVimeo-0.2.1.dist-info/metadata.json
PyVimeo-0.2.1.dist-info/RECORD
PyVimeo-0.2.1.dist-info/top_level.txt
PyVimeo-0.2.1.dist-info/WHEEL
vimeo/__init__.py
vimeo/client.py
vimeo/upload.py
vimeo/auth/__init__.py
vimeo/auth/authorization_code.py
vimeo/auth/base.py
vimeo/auth/client_credentials.py
