Metadata-Version: 1.1
Name: PyVimeo
Version: 0.2.1
Summary: Simple interaction with the Vimeo API.
Home-page: https://developer.vimeo.com/
Author: Vimeo
Author-email: support@vimeo.com
License: Apache License, Version 2.0, January 2004
Platform: UNKNOWN
Classifier: Development Status :: 4 - Beta
Classifier: Environment :: Console
Classifier: Environment :: Web Environment
Classifier: Intended Audience :: End Users/Desktop
Classifier: Intended Audience :: Developers
Classifier: Operating System :: OS Independent
Classifier: Programming Language :: Python
Classifier: Topic :: Internet
Classifier: Topic :: Multimedia :: Video
Classifier: Topic :: Software Development :: Libraries :: Python Modules
